django_html_dumper-0.2.6.dist-info/DESCRIPTION.rst
django_html_dumper-0.2.6.dist-info/METADATA
django_html_dumper-0.2.6.dist-info/RECORD
django_html_dumper-0.2.6.dist-info/WHEEL
django_html_dumper-0.2.6.dist-info/metadata.json
django_html_dumper-0.2.6.dist-info/top_level.txt
html_dumper/__init__.py
html_dumper/apps.py
html_dumper/models.py
html_dumper/views.py
html_dumper/management/__init__.py
html_dumper/management/commands/__init__.py
html_dumper/management/commands/dump_html.py
html_dumper/templates/html_dumper/base.html
