Metadata-Version: 2.0
Name: django-html-dumper
Version: 0.2.6
Summary: Dumps html pages and their corresponding assets into a tar file
Home-page: https://github.com/adrienbrunet/django-html-dumper
Author: Adrien Brunet
Author-email: adrien@emencia.com
License: MIT
Keywords: django-html-dumper
Platform: UNKNOWN
Classifier: Development Status :: 3 - Alpha
Classifier: Framework :: Django
Classifier: Framework :: Django :: 1.11
Classifier: Intended Audience :: Developers
Classifier: License :: OSI Approved :: BSD License
Classifier: Natural Language :: English
Classifier: Programming Language :: Python :: 2
Classifier: Programming Language :: Python :: 2.7
Classifier: Programming Language :: Python :: 3
Classifier: Programming Language :: Python :: 3.4
Classifier: Programming Language :: Python :: 3.5
